takprotobuf/__init__.py
takprotobuf/parseProto.py
takprotobuf/xmlToProto.py
takprotobuf/proto/__init__.py
takprotobuf/proto/contact_pb2.py
takprotobuf/proto/cotevent_pb2.py
takprotobuf/proto/detail_pb2.py
takprotobuf/proto/group_pb2.py
takprotobuf/proto/precisionlocation_pb2.py
takprotobuf/proto/status_pb2.py
takprotobuf/proto/takcontrol_pb2.py
takprotobuf/proto/takmessage_pb2.py
takprotobuf/proto/takv_pb2.py
takprotobuf/proto/track_pb2.py
takprotobuf-0.0.1.dist-info/LICENSE.md
takprotobuf-0.0.1.dist-info/METADATA
takprotobuf-0.0.1.dist-info/WHEEL
takprotobuf-0.0.1.dist-info/top_level.txt
takprotobuf-0.0.1.dist-info/RECORD
