Metadata-Version: 2.1
Name: takprotobuf
Version: 0.0.1
Summary: A Python library to encode and decode Cursor-on-Target (CoT) messages using Protocol Buffers.
Home-page: https://github.com/DeltaBravo15/takprotobuf
Author: Delta Bravo-15
Author-email: deltabravo15ga@gmail.com
License: UNKNOWN
Keywords: TAK,ATAK,WinTAK,Python,Opensource
Platform: UNKNOWN
Classifier: Programming Language :: Python :: 3
Classifier: License :: OSI Approved :: MIT License
Classifier: Operating System :: OS Independent
Requires-Python: >=3.6
Requires-Dist: untangle
Requires-Dist: lxml
